{"stats":{"total":33,"passed":32,"retries":1,"failed":1},"status":"failed","newTests":[{"id":"9b4e96a2fa12b1a22effcdd00ce345a9","name":"Validate that Cart Page can be opened in Inventory Page","status":"passed","duration":624},{"id":"3178f197fe227e60efb449142705a2cb","name":"Validate that Cart Page can be opened in Product Details Page","status":"passed","duration":752},{"id":"c030fcf604af0ce35f8208ed99a300f4","name":"Validate that correct item details - Title, Description, and Price are displayed in Cart Page","status":"passed","duration":1098},{"id":"8ef43e8d982977b77d0b5691a105098e","name":"Validate that Product Detail Page is opened by clicking the item title in Cart Page","status":"passed","duration":1013},{"id":"b12f1ec541a206153020760864cc5789","name":"Validate that Checkout button is disabled when the cart is empty","status":"failed","duration":5956},{"id":"1f95bda72118443370b4f6d0d748e69c","name":"Validate that Checkout button is disabled when the cart is empty","status":"failed","duration":5991},{"id":"c1c88c87b60a8749b722e0447238dd00","name":"Validate that Checkout button is disabled when the cart is empty","status":"failed","duration":6002},{"id":"ee755749dc7084f14e1250727351d7be","name":"Validate that Cart Badge Number matches the number of listed items in Cart Page","status":"passed","duration":1553},{"id":"00c9d6cb2a762aa2428bd15707e25b3b","name":"Validate that user can navigate back to Inventory Page using Continue Shopping button","status":"passed","duration":718},{"id":"42704872687e8670f7045a0e379d7a4a","name":"Validate that user can navigate back to Inventory Page using Browser Back Button","status":"passed","duration":713},{"id":"c9076684237e4a8f2b86fdd2dae13786","name":"Validate that item in Cart Page can be removed","status":"passed","duration":897},{"id":"5616ba038ea16a5fb27b99991c7f07d2","name":"Validate that correct product details - title, description, and the price are displayed when opened using Product Title","status":"passed","duration":760},{"id":"a2be31c0bc20de8b614b59309b5ca906","name":"Validate that correct product details - title, description, and the price are displayed when opened using Product Image","status":"passed","duration":766},{"id":"baf6bf42bc57baa0eb881b602d0fa377","name":"Validate that user can navigate back to Inventory Page using Back Button","status":"passed","duration":676},{"id":"17f611dcb797ee037d2a4508b782ac4d","name":"Validate that user can navigate back to Inventory Page using Browser Back Button","status":"passed","duration":607},{"id":"372876a3c8b9f5f95914dd28429b42e0","name":"Validate that item can be added","status":"passed","duration":647},{"id":"a9394b811e5dbd353197f98940cc6117","name":"Validate that added item can be removed","status":"passed","duration":832},{"id":"9fb426653a1c237a4e1b4c1b72c89dab","name":"Validate that each product has the title, description, and the price displayed","status":"passed","duration":722},{"id":"28aab8f2a6c081bc06ce5fa39f14abe4","name":"Validate that cart counter is incremented by 1 after adding 1 item","status":"passed","duration":769},{"id":"19ee967e27e625f6be216e68fbea7e58","name":"Validate that cart counter is incremented based on the number of multiple items added","status":"passed","duration":822},{"id":"dafd6856be76699bd6369d83868a9605","name":"Validate that cart counter is decremented by 1 after removing 1 item","status":"passed","duration":802},{"id":"2c4a4fc31cfb98d2ec75a81c6dce2488","name":"Validate that cart counter is decremented based on the number of multiple items removed","status":"passed","duration":778},{"id":"546e5000a80dc496a7b09529b21be781","name":"Validate that products details can be viewed or opened in Product View Page by clicking Product Title","status":"passed","duration":711},{"id":"b157e6400538459a3876996b739cbd49","name":"Validate that products details can be viewed or opened in Product View Page by clicking Product Image","status":"passed","duration":741},{"id":"28e593a36e1d3b0d63f8e58408b28142","name":"Validate that products are sorted by Name (A to Z)","status":"passed","duration":705},{"id":"bff9c972a3a3e938005f743cb1a12c11","name":"Validate that products are sorted by Name (Z to A)","status":"passed","duration":750},{"id":"4bee68bf439570ec49aa96df7fa69810","name":"Validate that products are sorted by Price (low to high)","status":"passed","duration":705},{"id":"2d4d513ac7d331c1400b9800761c03b2","name":"Validate that products are sorted by Price (high to low)","status":"passed","duration":721},{"id":"03e1c7cacff776e4a2dafc0597f97aaa","name":"Validate that username is required","status":"passed","duration":571},{"id":"48fdeb10eef71e8b102ebd88c5677f38","name":"Validate that password is required","status":"passed","duration":500},{"id":"6363881b9b801f2288963c682c8273b4","name":"Validate that error message for locked out user is displayed","status":"passed","duration":527},{"id":"2e48481235fc41ce341aa0f0fc6cbdb8","name":"Validate that error message for wrong password is displayed","status":"passed","duration":515},{"id":"a051f3aa9a6b11d9948ac2d29c7d2866","name":"Validate that user is successfully logged in","status":"passed","duration":596},{"id":"d4676d182661fae666b9960a680be4b8","name":"Validate that error message is displayed after navigating to Inventory without logging in","status":"passed","duration":530},{"id":"cb4e704cf9e3a7a3645704e9541101b0","name":"Validate that user is back to Log In screen after Log out","status":"passed","duration":1495}],"flakyTests":[],"retryTests":[],"name":"Allure Report – Pull request #5","duration":30618,"createdAt":1773116366956,"plugin":"Awesome","meta":{"reportId":"63a5edf9-7dab-4db9-b3b8-a2072a1e4df1","singleFile":false,"withTestResultsLinks":true},"pullRequestHref":"https://github.com/allyzs/sauce-demo-playwright-javascript/pull/5","jobHref":"https://github.com/allyzs/sauce-demo-playwright-javascript/actions/runs/22886732179"}